random_stuff/__init__.py
random_stuff/person.py
the_person_package-0.0.1.dist-info/METADATA
the_person_package-0.0.1.dist-info/WHEEL
the_person_package-0.0.1.dist-info/top_level.txt
the_person_package-0.0.1.dist-info/RECORD
