Metadata-Version: 2.1
Name: the-person-package
Version: 0.0.1
Summary: My first Python package
Author: mustafa hakimi
Author-email: test@test.com
Classifier: Programming Language :: Python :: 3
Classifier: License :: OSI Approved :: MIT License
Classifier: Operating System :: OS Independent
Requires-Python: >=3.6
